tdxapi/__init__.py
tdxapi/client.py
tdxapi/dispatcher.py
tdxapi/enums/__init__.py
tdxapi/enums/aggregate_function.py
tdxapi/enums/article_status.py
tdxapi/enums/attachment_type.py
tdxapi/enums/backing_item_type.py
tdxapi/enums/column_data_type.py
tdxapi/enums/component.py
tdxapi/enums/component_function.py
tdxapi/enums/conflict_type.py
tdxapi/enums/feed_item_type.py
tdxapi/enums/license_type.py
tdxapi/enums/sla_start_basis.py
tdxapi/enums/status_class.py
tdxapi/enums/ticket_class.py
tdxapi/enums/ticket_task_type.py
tdxapi/enums/time_zone.py
tdxapi/enums/unmet_constraint_search_type.py
tdxapi/enums/update_type.py
tdxapi/enums/user_type.py
tdxapi/managers/__init__.py
tdxapi/managers/account.py
tdxapi/managers/application.py
tdxapi/managers/asset.py
tdxapi/managers/asset_app.py
tdxapi/managers/asset_status.py
tdxapi/managers/attachment.py
tdxapi/managers/bases.py
tdxapi/managers/configuration_item.py
tdxapi/managers/configuration_item_type.py
tdxapi/managers/configuration_relationship_type.py
tdxapi/managers/custom_attribute.py
tdxapi/managers/custom_attribute_choice.py
tdxapi/managers/functional_role.py
tdxapi/managers/group.py
tdxapi/managers/helpers.py
tdxapi/managers/impact.py
tdxapi/managers/location.py
tdxapi/managers/location_room.py
tdxapi/managers/mixins.py
tdxapi/managers/priority.py
tdxapi/managers/product_model.py
tdxapi/managers/product_type.py
tdxapi/managers/report.py
tdxapi/managers/resource_pool.py
tdxapi/managers/security_role.py
tdxapi/managers/ticket.py
tdxapi/managers/ticket_app.py
tdxapi/managers/ticket_source.py
tdxapi/managers/ticket_status.py
tdxapi/managers/ticket_task.py
tdxapi/managers/ticket_type.py
tdxapi/managers/urgency.py
tdxapi/managers/vendor.py
tdxapi/models/__init__.py
tdxapi/models/account.py
tdxapi/models/account_search.py
tdxapi/models/application.py
tdxapi/models/asset.py
tdxapi/models/asset_search.py
tdxapi/models/asset_status.py
tdxapi/models/asset_status_search.py
tdxapi/models/attachment.py
tdxapi/models/bases.py
tdxapi-0.10.0.dist-info/LICENSE
tdxapi-0.10.0.dist-info/WHEEL
tdxapi-0.10.0.dist-info/METADATA
tdxapi-0.10.0.dist-info/RECORD
