Metadata-Version: 2.1
Name: tdxapi
Version: 0.10.0
Summary: A Python TeamDynamix API wrapper
Home-page: https://gitlab.com/placcd/tdxapi
License: GPL-3.0-or-later
Keywords: teamdynamix,webapi,tdxapi
Author: Marcelo Bajana Jr
Author-email: placcd@tuta.io
Requires-Python: >=3.6.1,<4.0.0
Classifier: Development Status :: 3 - Alpha
Classifier: License :: OSI Approved :: GNU General Public License v3 or later (GPLv3+)
Classifier: Programming Language :: Python :: 3
Classifier: Programming Language :: Python :: 3.10
Classifier: Programming Language :: Python :: 3.6
Classifier: Programming Language :: Python :: 3.7
Classifier: Programming Language :: Python :: 3.8
Classifier: Programming Language :: Python :: 3.9
Classifier: Topic :: Software Development :: Libraries
Requires-Dist: attrs (>=20.1.0,<21.0.0)
Requires-Dist: python-dateutil (>=2.8.1,<3.0.0)
Requires-Dist: requests (>=2.23.0,<3.0.0)
Project-URL: Repository, https://gitlab.com/placcd/tdxapi
